kttc/__init__.py
kttc/__main__.py
kttc/py.typed
kttc/agents/__init__.py
kttc/agents/accuracy.py
kttc/agents/base.py
kttc/agents/consensus.py
kttc/agents/context.py
kttc/agents/domain_profiles.py
kttc/agents/dynamic_selector.py
kttc/agents/fluency.py
kttc/agents/fluency_chinese.py
kttc/agents/fluency_english.py
kttc/agents/fluency_russian.py
kttc/agents/hallucination.py
kttc/agents/orchestrator.py
kttc/agents/orchestrator_v2.py
kttc/agents/parser.py
kttc/agents/terminology.py
kttc/cli/__init__.py
kttc/cli/demo.py
kttc/cli/main.py
kttc/cli/ui.py
kttc/cli/commands/__init__.py
kttc/cli/commands/benchmark.py
kttc/cli/commands/compare.py
kttc/cli/commands/glossary.py
kttc/cli/formatters/__init__.py
kttc/cli/formatters/html.py
kttc/cli/formatters/markdown.py
kttc/core/__init__.py
kttc/core/batch_processor.py
kttc/core/correction.py
kttc/core/glossary.py
kttc/core/models.py
kttc/core/mqm.py
kttc/core/refinement.py
kttc/helpers/__init__.py
kttc/helpers/base.py
kttc/helpers/chinese.py
kttc/helpers/detection.py
kttc/helpers/english.py
kttc/helpers/russian.py
kttc/llm/__init__.py
kttc/llm/anthropic_provider.py
kttc/llm/base.py
kttc/llm/complexity_router.py
kttc/llm/gigachat_provider.py
kttc/llm/model_selector.py
kttc/llm/openai_provider.py
kttc/llm/yandex_provider.py
kttc/llm/prompts/__init__.py
kttc/memory/__init__.py
kttc/memory/termbase.py
kttc/memory/tm.py
kttc/metrics/__init__.py
kttc/training/__init__.py
kttc/training/domain_adapter.py
kttc/utils/__init__.py
kttc/utils/config.py
kttc/utils/dependencies.py
kttc/utils/languages.py
kttc/webui/__init__.py
kttc/webui/server.py
kttc-0.2.2.dist-info/licenses/LICENSE
kttc-0.2.2.dist-info/licenses/NOTICE
kttc-0.2.2.dist-info/METADATA
kttc-0.2.2.dist-info/WHEEL
kttc-0.2.2.dist-info/entry_points.txt
kttc-0.2.2.dist-info/top_level.txt
kttc-0.2.2.dist-info/RECORD
