Metadata-Version: 2.4
Name: kttc
Version: 0.2.2
Summary: Knowledge Translation Transmutation Core - Transforming translations into gold-standard quality
Author-email: KTTC AI <dev@kt.tc>
License: Apache-2.0
Project-URL: Homepage, https://github.com/kttc-ai/kttc
Project-URL: Repository, https://github.com/kttc-ai/kttc
Project-URL: Issues, https://github.com/kttc-ai/kttc/issues
Keywords: translation,qa,quality-assurance,llm,agents,automation
Classifier: Development Status :: 3 - Alpha
Classifier: Intended Audience :: Developers
Classifier: License :: OSI Approved :: Apache Software License
Classifier: Programming Language :: Python :: 3.11
Classifier: Programming Language :: Python :: 3.12
Classifier: Topic :: Software Development :: Quality Assurance
Classifier: Topic :: Software Development :: Testing
Requires-Python: >=3.11
License-File: LICENSE
License-File: NOTICE
Requires-Dist: typer>=0.20.0
Requires-Dist: rich>=14.2.0
Requires-Dist: pydantic>=2.12.4
Requires-Dist: pydantic-settings>=2.11.0
Requires-Dist: aiohttp>=3.13.2
Requires-Dist: openai>=2.7.1
Requires-Dist: anthropic>=0.72.0
Requires-Dist: aiosqlite>=0.21.0
Requires-Dist: orjson>=3.11.4
Requires-Dist: fastapi>=0.121.1
Requires-Dist: uvicorn>=0.38.0
Requires-Dist: websockets>=15.0.1
Requires-Dist: sacrebleu>=2.5.1
Requires-Dist: mtdata>=0.4.3
Requires-Dist: mawo-pymorphy3>=1.0.4
Requires-Dist: mawo-razdel>=1.0.6
Requires-Dist: mawo-slovnet>=1.0.7
Requires-Dist: mawo-natasha>=1.0.3
Requires-Dist: spacy<3.9.0,>=3.8.0
Requires-Dist: jieba>=0.42
Provides-Extra: metrics
Requires-Dist: sentence-transformers>=5.1.2; extra == "metrics"
Provides-Extra: english
Requires-Dist: language-tool-python>=2.9.5; extra == "english"
Provides-Extra: chinese
Requires-Dist: hanlp>=2.1.3; extra == "chinese"
Provides-Extra: all-languages
Requires-Dist: language-tool-python>=2.9.5; extra == "all-languages"
Requires-Dist: hanlp>=2.1.3; extra == "all-languages"
Provides-Extra: dev
Requires-Dist: pytest>=9.0.0; extra == "dev"
Requires-Dist: pytest-cov>=7.0.0; extra == "dev"
Requires-Dist: pytest-xdist>=3.8.0; extra == "dev"
Requires-Dist: pytest-asyncio>=0.23.0; extra == "dev"
Requires-Dist: black>=25.11.0; extra == "dev"
Requires-Dist: ruff>=0.14.4; extra == "dev"
Requires-Dist: mypy>=1.18.2; extra == "dev"
Requires-Dist: pre-commit>=4.4.0; extra == "dev"
Requires-Dist: types-requests>=2.32.4; extra == "dev"
Requires-Dist: types-tqdm>=4.67.0; extra == "dev"
Dynamic: license-file
